pyNSRDB/__init__.py
pyNSRDB/credentials.py
pyNSRDB/data.py
pyNSRDB/requests.py
pyNSRDB/response.py
pyNSRDB-0.1.1.dist-info/LICENSE
pyNSRDB-0.1.1.dist-info/METADATA
pyNSRDB-0.1.1.dist-info/WHEEL
pyNSRDB-0.1.1.dist-info/top_level.txt
pyNSRDB-0.1.1.dist-info/RECORD
