Metadata-Version: 2.1
Name: pyNSRDB
Version: 0.1.1
Summary: Python frontend to NREL NSRDB API.
Home-page: https://github.com/bwilliams2/pyNSRDB
Author: Bryce Williams
Author-email: bwilliams2@gmail.com
License: UNKNOWN
Platform: UNKNOWN
Classifier: Programming Language :: Python :: 3
Classifier: License :: OSI Approved :: MIT License
Classifier: Operating System :: OS Independent
Requires-Python: >=3.6
License-File: LICENSE
Requires-Dist: pandas (>=1.2)
Requires-Dist: shapely (>=1.6)
Requires-Dist: python-dotenv
Requires-Dist: requests
